AUTHORS.md
HISTORY.md
LICENSE
README.md
docs/api.md
docs/deployment.md
docs/history.md
docs/index.md
docs/usage.md
omega/__init__.py
omega/app.py
omega/cli.py
omega/config/__init__.py
omega/config/defaults.yaml
omega/config/dev.yaml
omega/config/schema.py
omega/config/sql/init.sql
omega/core/__init__.py
omega/core/accelerate.py
omega/core/events.py
omega/core/sanity.py
omega/fetcher/__init__.py
omega/fetcher/abstract_quotes_fetcher.py
omega/fetcher/archive.py
omega/fetcher/quotes_fetcher.py
omega/interfaces/__init__.py
omega/interfaces/jobs.py
omega/interfaces/quotes.py
omega/interfaces/sys.py
omega/interfaces/websockets/__init__.py
omega/interfaces/websockets/base.py
omega/jobs/__init__.py
omega/jobs/__main__.py
omega/jobs/syncjobs.py
omega/logreceivers/__init__.py
omega/logreceivers/redis.py
tests/__init__.py
tests/test_cli.py
zillionare_omega-1.1.0.1.dist-info/entry_points.txt
zillionare_omega-1.1.0.1.dist-info/LICENSE
zillionare_omega-1.1.0.1.dist-info/WHEEL
zillionare_omega-1.1.0.1.dist-info/METADATA
zillionare_omega-1.1.0.1.dist-info/RECORD
