Metadata-Version: 2.1
Name: zillionare-omega
Version: 1.1.0.1
Summary: 高速分布式行情服务器
Home-page: https://zillionare-omega.readthedocs.io
License: MIT
Keywords: AI,quant,trade,stock
Author: jieyu
Author-email: code@jieyu.ai
Requires-Python: >=3.8,<3.9
Classifier: Development Status :: 3 - Alpha
Classifier: Intended Audience :: Developers
Classifier: License :: OSI Approved :: MIT License
Classifier: Natural Language :: English
Classifier: Programming Language :: Python :: 3
Classifier: Programming Language :: Python :: 3.8
Provides-Extra: dev
Provides-Extra: doc
Provides-Extra: test
Requires-Dist: APScheduler (==3.7.0)
Requires-Dist: aiocache (==0.11.1)
Requires-Dist: aiohttp (>=3.8.0)
Requires-Dist: aioredis (==1.3.1)
Requires-Dist: arrow (==0.15.8)
Requires-Dist: asyncpg (==0.21)
Requires-Dist: black (==20.8b1); extra == "test"
Requires-Dist: cfg4py (>=0.9.0,<0.10.0)
Requires-Dist: doc8 (==0.8.1); extra == "test"
Requires-Dist: fire (==0.4.0)
Requires-Dist: flake8 (==3.8.4); extra == "test"
Requires-Dist: gino (==1.0.1)
Requires-Dist: idna (==2.5)
Requires-Dist: isort (==5.6.4); extra == "test"
Requires-Dist: livereload (>=2.6.3,<3.0.0); extra == "doc"
Requires-Dist: mkdocs (>=1.1.2,<2.0.0); extra == "doc"
Requires-Dist: mkdocs-autorefs (==0.1.1); extra == "doc"
Requires-Dist: mkdocs-include-markdown-plugin (>=1.0.0,<2.0.0); extra == "doc"
Requires-Dist: mkdocs-material (>=6.1.7,<7.0.0); extra == "doc"
Requires-Dist: mkdocs-material-extensions (>=1.0.1,<2.0.0)
Requires-Dist: mkdocstrings (>=0.13.6,<0.14.0); extra == "doc"
Requires-Dist: numpy (==1.20.1)
Requires-Dist: pandas (==1.2.3)
Requires-Dist: pip (>=20.3.1,<21.0.0); extra == "dev"
Requires-Dist: pre-commit (==2.8.2); extra == "dev"
Requires-Dist: psutil (==5.8.0)
Requires-Dist: pyarrow (==2.0.0)
Requires-Dist: pyemit (==0.4.5)
Requires-Dist: pytest (==6.1.2); extra == "test"
Requires-Dist: pytest-cov (==2.10.1); extra == "test"
Requires-Dist: rlog (==0.3)
Requires-Dist: sanic (==20.12.2)
Requires-Dist: sh (==1.14.1)
Requires-Dist: tox (>=3.20.1,<4.0.0); extra == "dev"
Requires-Dist: twine (>=3.3.0,<4.0.0); extra == "dev"
Requires-Dist: virtualenv (>=20.2.2,<21.0.0); extra == "dev"
Requires-Dist: xxhash (==2.0.0)
Requires-Dist: zillionare_omega_adaptors_jq (==1.0.5)
Requires-Dist: zillionare_omicron (==1.1.0.1)
Project-URL: Documentation, https://zillionare-omega.readthedocs.io
Project-URL: Repository, https://github.com/zillionare/omega
